devcycle_python_sdk/VERSION.txt
devcycle_python_sdk/__init__.py
devcycle_python_sdk/bucketing-lib.release.wasm
devcycle_python_sdk/cloud_client.py
devcycle_python_sdk/devcycle_client.py
devcycle_python_sdk/exceptions.py
devcycle_python_sdk/local_client.py
devcycle_python_sdk/options.py
devcycle_python_sdk/py.typed
devcycle_python_sdk/api/__init__.py
devcycle_python_sdk/api/backoff.py
devcycle_python_sdk/api/bucketing_client.py
devcycle_python_sdk/api/config_client.py
devcycle_python_sdk/api/event_client.py
devcycle_python_sdk/api/local_bucketing.py
devcycle_python_sdk/managers/__init__.py
devcycle_python_sdk/managers/config_manager.py
devcycle_python_sdk/managers/eval_hooks_manager.py
devcycle_python_sdk/managers/event_queue_manager.py
devcycle_python_sdk/managers/sse_manager.py
devcycle_python_sdk/models/__init__.py
devcycle_python_sdk/models/bucketed_config.py
devcycle_python_sdk/models/config_metadata.py
devcycle_python_sdk/models/environment_metadata.py
devcycle_python_sdk/models/error_response.py
devcycle_python_sdk/models/eval_hook.py
devcycle_python_sdk/models/eval_hook_context.py
devcycle_python_sdk/models/eval_reason.py
devcycle_python_sdk/models/event.py
devcycle_python_sdk/models/feature.py
devcycle_python_sdk/models/platform_data.py
devcycle_python_sdk/models/project_metadata.py
devcycle_python_sdk/models/user.py
devcycle_python_sdk/models/variable.py
devcycle_python_sdk/models/variable_metadata.py
devcycle_python_sdk/open_feature_provider/__init__.py
devcycle_python_sdk/open_feature_provider/provider.py
devcycle_python_sdk/protobuf/__init__.py
devcycle_python_sdk/protobuf/utils.py
devcycle_python_sdk/protobuf/variableForUserParams_pb2.py
devcycle_python_sdk/protobuf/variableForUserParams_pb2.pyi
devcycle_python_sdk/util/__init__.py
devcycle_python_sdk/util/strings.py
devcycle_python_sdk/util/version.py
devcycle_python_server_sdk-3.13.5.dist-info/licenses/LICENSE
example/__init__.py
example/cloud_client_example.py
example/local_bucketing_client_example.py
example/openfeature_example.py
test/__init__.py
devcycle_python_server_sdk-3.13.5.dist-info/METADATA
devcycle_python_server_sdk-3.13.5.dist-info/WHEEL
devcycle_python_server_sdk-3.13.5.dist-info/top_level.txt
devcycle_python_server_sdk-3.13.5.dist-info/RECORD
