Metadata-Version: 2.4
Name: devcycle-python-server-sdk
Version: 3.13.5
Summary: DevCycle Python SDK
Home-page: https://github.com/devcycleHQ/python-server-sdk
Author-email: 
Keywords: DevCycle
Requires-Python: >=3.9
License-File: LICENSE
Requires-Dist: setuptools>=21.0.0
Requires-Dist: urllib3>=1.15.1
Requires-Dist: requests>=2.32
Requires-Dist: wasmtime~=30.0.0
Requires-Dist: protobuf>=4.23.3
Requires-Dist: openfeature-sdk~=0.8.0
Requires-Dist: launchdarkly-eventsource>=1.2.1
Requires-Dist: responses>=0.23.1
Dynamic: description
Dynamic: home-page
Dynamic: keywords
Dynamic: license-file
Dynamic: requires-dist
Dynamic: requires-python
Dynamic: summary
